data_from_files/__init__.py
data_from_files/constants.py
data_from_files/datatypes.py
data_from_files/fixtures.py
data_from_files/hooks.py
data_from_files/loader.py
data_from_files/modinfo.py
pytest_data_from_files-0.2.0.dist-info/LICENSE.MIT
pytest_data_from_files-0.2.0.dist-info/METADATA
pytest_data_from_files-0.2.0.dist-info/WHEEL
pytest_data_from_files-0.2.0.dist-info/entry_points.txt
pytest_data_from_files-0.2.0.dist-info/top_level.txt
pytest_data_from_files-0.2.0.dist-info/RECORD
