Metadata-Version: 2.1
Name: pytest-data-from-files
Version: 0.2.0
Summary: pytest plugin to provide data from files loaded automatically
Home-page: https://github.com/ssato/pytest-data-from-files
Author: Satoru SATOH
Author-email: satoru.satoh@gmail.com
Maintainer: Satoru SATOH
Maintainer-email: satoru.satoh@gmail.com
License: MIT
Project-URL: CI: Github Actions, https://github.com/ssato/pytest-data-from-files/actions
Project-URL: Download, https://pypi.python.org/pypi/pytest-data-from-files
Project-URL: Bug Tracker, https://github.com/ssato/pytest-data-from-files/issues
Project-URL: Source, https://github.com/ssato/pytest-data-from-files
Platform: UNKNOWN
Classifier: Development Status :: 4 - Beta
Classifier: Intended Audience :: Developers
Classifier: License :: OSI Approved :: MIT License
Classifier: Programming Language :: Python
Classifier: Programming Language :: Python :: 3
Classifier: Programming Language :: Python :: 3.6
Classifier: Programming Language :: Python :: 3.7
Classifier: Programming Language :: Python :: 3.8
Classifier: Programming Language :: Python :: 3.9
Classifier: Environment :: Console
Classifier: Operating System :: OS Independent
Classifier: Topic :: Software Development :: Testing
Classifier: Topic :: Utilities
Classifier: Framework :: Pytest
Requires-Dist: pytest
